lorem_bot-0.0.1.dist-info/METADATA
lorem_bot-0.0.1.dist-info/RECORD
lorem_bot-0.0.1.dist-info/WHEEL
lorem_bot-0.0.1.dist-info/top_level.txt
lorembot/__init__.py
lorembot/function.py
lorembot/setFunction.py
